newsdatascraper/__init__.py
newsdatascraper/models.py
newsdatascraper/scraper.py
newsdatascraper-0.0.2.dist-info/LICENSE
newsdatascraper-0.0.2.dist-info/METADATA
newsdatascraper-0.0.2.dist-info/WHEEL
newsdatascraper-0.0.2.dist-info/top_level.txt
newsdatascraper-0.0.2.dist-info/RECORD
