Metadata-Version: 2.1
Name: newsdatascraper
Version: 0.0.2
Summary: Easily query articles
Home-page: https://github.com/erikqu/NewsDataScraper
Author: Erick Torres and Erik Quintanilla
Author-email: ericktorresdeveloper@gmail.com
License: MIT
Platform: UNKNOWN
Classifier: Programming Language :: Python :: 3.5
Classifier: Natural Language :: English
Classifier: Development Status :: 3 - Alpha
Classifier: License :: OSI Approved :: MIT License
Classifier: Intended Audience :: Developers
Requires-Dist: requests (==2.20.0)
Requires-Dist: httmock (==1.3.0)
Requires-Dist: newspaper3k (==0.2.8)
Requires-Dist: tests (==0.007)
